min_poetry_template/application/cli/cli.py
min_poetry_template-0.0.5.dist-info/METADATA
min_poetry_template-0.0.5.dist-info/WHEEL
min_poetry_template-0.0.5.dist-info/entry_points.txt
min_poetry_template-0.0.5.dist-info/RECORD
