Metadata-Version: 2.1
Name: min-poetry-template
Version: 0.0.5
Summary: An example package using poetry as a package manager.
License: MIT
Author: michael
Author-email: michael__brown@tutanota.com
Requires-Python: >=3.11,<4.0
Classifier: License :: OSI Approved :: MIT License
Classifier: Programming Language :: Python :: 3
Classifier: Programming Language :: Python :: 3.11
Requires-Dist: termcolor (>=2.3.0,<3.0.0)
